Metadata-Version: 2.1
Name: privacyfighter
Version: 2.0.1
Summary: Privacy-Fighter: A Browser Setup For Increased Privacy And Security
Home-page: https://github.com/jotyGill/privacy-fighter
Author: JGill
Author-email: joty@mygnu.org
License: GNU General Public License v3 or later (GPLv3+)
Project-URL: Why Privacy Matters, https://github.com/jotyGill/privacy
Project-URL: github, https://github.com/jotyGill/privacy-fighter
Project-URL: gitlab, https://gitlab.com/JGill/privacy-fighter
Keywords: privacy,firefox,browser
Platform: GNU/Linux
Platform: Ubuntu
Platform: Debian
Platform: Kali
Platform: CentOS
Platform: Arch
Platform: Fedora
Classifier: Intended Audience :: End Users/Desktop
Classifier: Intended Audience :: System Administrators
Classifier: Intended Audience :: Information Technology
Classifier: Topic :: Utilities
Classifier: License :: OSI Approved :: GNU General Public License v3 or later (GPLv3+)
Classifier: Natural Language :: English
Classifier: Operating System :: OS Independent
Classifier: Operating System :: POSIX :: Linux
Classifier: Operating System :: Microsoft
Classifier: Operating System :: MacOS
Classifier: Programming Language :: Python :: 3 :: Only
Classifier: Programming Language :: Python :: 3.5
Classifier: Programming Language :: Python :: 3.6
Classifier: Programming Language :: Python :: 3.7
Classifier: Topic :: Internet
Classifier: Topic :: Internet :: WWW/HTTP :: Browsers
Classifier: Topic :: Security
Requires-Python: >=3.5
